i2llservice/__init__.py
i2llservice/client.py
i2llservice/config.py
i2llservice/server.py
i2llservice/utils.py
i2llserver-1.1.1.dist-info/LICENCE
i2llserver-1.1.1.dist-info/METADATA
i2llserver-1.1.1.dist-info/WHEEL
i2llserver-1.1.1.dist-info/entry_points.txt
i2llserver-1.1.1.dist-info/top_level.txt
i2llserver-1.1.1.dist-info/RECORD
