Metadata-Version: 2.1
Name: i2llserver
Version: 1.1.1
Summary: Server of LockingLock project
Home-page: https://github.com/i2cy/LockingLock_Python
Author: I2cy Cloud
Author-email: i2cy@outlook.com
License: UNKNOWN
Project-URL: Bug Tracker, https://github.com/i2cy/LockingLock_Python/issues
Project-URL: Source Code, https://github.com/i2cy/LockingLock_Python
Project-URL: Documentation, https://github.com/i2cy/LockingLock_Python/blob/master/README.md
Platform: UNKNOWN
Classifier: Programming Language :: Python :: 3
Classifier: License :: OSI Approved :: MIT License
Classifier: Operating System :: OS Independent
Requires-Python: >=3.6
License-File: LICENCE
Requires-Dist: i2cylib (>=1.12.0)
Requires-Dist: paho-mqtt
